openomics/__init__.py
openomics/clinical.py
openomics/genomics.py
openomics/imageomics.py
openomics/multicohorts.py
openomics/multiomics.py
openomics/proteomics.py
openomics/transcriptomics.py
openomics_web/__init__.py
openomics_web/app.py
openomics_web/callbacks.py
openomics_web/server.py
openomics-0.8.9.dist-info/LICENSE
openomics-0.8.9.dist-info/METADATA
openomics-0.8.9.dist-info/WHEEL
openomics-0.8.9.dist-info/top_level.txt
openomics-0.8.9.dist-info/RECORD
