Metadata-Version: 2.1
Name: openomics
Version: 0.8.9
Summary: OpenOmics provides a bioinformatics API and web-app platform integrate and visualize the multiomics and clinical data.
Home-page: https://github.com/JonnyTran/OpenOmics
Author: Jonny Tran
License: MIT
Keywords: sample,example,setuptools
Classifier: Development Status :: 3 - Alpha
Classifier: Intended Audience :: Developers
Classifier: License :: OSI Approved :: MIT License
Classifier: Operating System :: OS Independent
Classifier: Programming Language :: Python :: 3
Classifier: Programming Language :: Python :: 3.7
Classifier: Programming Language :: Python :: 3.8
Classifier: Programming Language :: Python :: 3.9
Classifier: Topic :: Software Development :: Libraries :: Python Modules
Requires-Python: <4,>=3.6
License-File: LICENSE
Requires-Dist: numpy
Requires-Dist: pandas
Requires-Dist: dask
Requires-Dist: networkx
Requires-Dist: scipy
Requires-Dist: astropy
Requires-Dist: biopython
Requires-Dist: bioservices
Requires-Dist: pyfaidx
Requires-Dist: goatools
Requires-Dist: obonet
Requires-Dist: gtfparse
Requires-Dist: h5py (!=3.7.0)
Requires-Dist: lxml (>=4.9.1)
Requires-Dist: gunicorn
Requires-Dist: six
Requires-Dist: validators
Requires-Dist: sqlalchemy
Requires-Dist: filetype
Requires-Dist: rarfile
Requires-Dist: logzero
Requires-Dist: tqdm
Requires-Dist: itsdangerous
Requires-Dist: bokeh
Requires-Dist: matplotlib
Requires-Dist: dash
Requires-Dist: dash-daq
Requires-Dist: dash-bootstrap-components
Provides-Extra: test
Requires-Dist: pip ; extra == 'test'
Requires-Dist: bumpversion ; extra == 'test'
Requires-Dist: wheel ; extra == 'test'
Requires-Dist: watchdog ; extra == 'test'
Requires-Dist: flake8 ; extra == 'test'
Requires-Dist: tox ; extra == 'test'
Requires-Dist: coverage ; extra == 'test'
Requires-Dist: twine ; extra == 'test'
Requires-Dist: pytest (>=7.3.0) ; extra == 'test'
Requires-Dist: pytest-runner ; extra == 'test'
Requires-Dist: pytest-cov ; extra == 'test'
Requires-Dist: Sphinx ; extra == 'test'
Requires-Dist: furo ; extra == 'test'
Requires-Dist: myst-parser ; extra == 'test'
Requires-Dist: sphinx-autodoc-typehints ; extra == 'test'
Requires-Dist: sphinx-inline-tabs ; extra == 'test'
Requires-Dist: sphinx-autobuild ; extra == 'test'
Requires-Dist: sphinx-copybutton ; extra == 'test'
Requires-Dist: sphinx-automodapi ; extra == 'test'
Requires-Dist: graphviz ; extra == 'test'
Requires-Dist: tqdm ; extra == 'test'
